shadertest/__init__.py
shadertest/builder.py
shadertest/graphics_context.py
shadertest/shader_function.py
shadertest/shader_parser.py
shadertest/type_map.py
shadertest-0.2.1.dist-info/LICENSE
shadertest-0.2.1.dist-info/METADATA
shadertest-0.2.1.dist-info/WHEEL
shadertest-0.2.1.dist-info/top_level.txt
shadertest-0.2.1.dist-info/RECORD
