Metadata-Version: 2.1
Name: shadertest
Version: 0.2.1
Summary: A Python library for unit testing GLSL functions
Home-page: https://github.com/Kupoman/shadertest
Author: Daniel Stokes
Author-email: stokes.daniel.j@gmail.com
License: UNKNOWN
Keywords: glsl unit test
Platform: UNKNOWN
Classifier: Development Status :: 2 - Pre-Alpha
Classifier: Intended Audience :: Developers
Classifier: License :: OSI Approved :: MIT License
Classifier: Operating System :: OS Independent
Classifier: Programming Language :: Python :: 3.7
Classifier: Topic :: Software Development :: Testing
Requires-Dist: PyOpenGL
Requires-Dist: PySDL2
